{
	"$schema": "../../../src/schemas/section.json",
	"name": "result",
	"content": [
		[
			"heading",
			{
				"text": "案例成效",
				"level": 1
			}
		],
		[
			"paragraph",
			[
				"基于AIGC的创作者系统，为创作者提供了全流程的创作工具和服务，重塑了从二创剪辑、转码、审核、发布到搜推一体的传播流程，实现了内容生产传播跨人群、跨终端、跨系统、跨业务的多跨协同、高效内聚的闭环管理。基于AIGC的创作者系统的知识产权成果显著，共申请了3项发明专利和1项软件著作权，并发表了2篇论文。这些成果体现了项目的技术创新性和实用性，也证明了项目在知识产权保护方面的重视和投入，为相关领域的技术发展、商业化和市场化提供了有力的支持和保障，同时也为该项目的后续发展提供了更多的机会和资源。自2023年4月基于AIGC的“Z视介”创作者系统上线以来，得到了广泛关注和应用，已有近百家MCN机构和两万多个人创作者入驻，内容日增量2000+，月播放量超3亿，社会效益和经济效益显著。"
			]
		]
	]
}
