{
	"$schema": "../../../src/schemas/section.json",
	"name": "method",
	"content": [
		[
			"heading",
			{
				"text": "案例做法",
				"level": 1
			}
		],
		[
			"paragraph",
			[
				"分展前、展中、展后三个部分。"
			]
		],
		[
			"paragraph",
			[
				"展前大数据集客，做好市场调研及规划。充分调研各品牌市场销量情况及核心诉求。在招商过程中，把每一个品牌的优势、劣势进行归纳整理，根据每个品牌的实际情况，规划展位排列以及展前宣传工作，将客户资源初步整合，优势互补。"
			]
		],
		[
			"paragraph",
			[
				"展中随时跟进各品牌销量数据并做个案分析。展中根据前期调研的品牌分析，进行精准定向客户邀约，并及时根据现场销量反馈，调整邀约策略及话术，并配合丰富有趣的互动活动来促进销量成交。"
			]
		],
		[
			"paragraph",
			[
				"展后收集各品牌销量数据及整体反馈，总结需要改进的不足及仍然可以保持的优势。并通过自建智能化预约上门试驾小程序，将展后客户数据二次转化。"
			]
		]
	]
}
