{
	"$schema": "../../../src/schemas/section.json",
	"name": "result",
	"content": [
		[
			"heading",
			{
				"text": "案例成效",
				"level": 1
			}
		],
		[
			"paragraph",
			[
				"中轴线一期视频全网发布后，总阅读量近1000万。传播总量776.7万，微博话题阅读量600余万，总播放量55.7万。多平台反响亮眼，获B站首页置顶展示及push推荐、优酷资讯页首页推荐、知乎专题收录，广受用户好评。以下为作品刊播后的社会影响，转载、引用情况："
			]
		],
		[
			"paragraph",
			[
				"2022年11月7日，参加由北京市文物局、北京中轴线申遗保护工作办公室主办的“数字传承，链接未来”纪念《保护世界文化和自然遗产公约》50周年主题活动。"
			]
		],
		[
			"paragraph",
			[
				"以《VR动画|360°全景转动北京中轴线》为首的中轴线系列视频获网信办支持，多家北京市属媒体积极转发，以及北京中轴线申遗办微博微信、北京文物局微信同步发布推荐。"
			]
		],
		[
			"paragraph",
			[
				"该视频在用户群体中也获得广泛好评，特别是VR技术给用户带来新颖的视觉体验，让观众在好玩的互动体验中感受到北京中轴线的历史底蕴。用户在观看这条视频时，可以转动手机或滑动屏幕，实现上下、左右、放大、缩小无死角浏览的视频效果，体验身临其境之感，这种交互方式更有吸引力，也更具新意，对用户来说也是一次全新的体验。"
			]
		]
	]
}
