{
	"$schema": "../../../src/schemas/section.json",
	"name": "0-preface",
	"content": [
		[
			"heading",
			{
				"text": "引言"
			}
		],
		[
			"paragraph",
			[
				"2024年11月11日至12日，首届“全球南方”媒体智库高端论坛在巴西圣保罗举行。本次论坛以“唱响‘全球南方’主旋律，开启发展振兴新征程”为主题，吸引了来自70多个国家和地区的170家媒体、智库、政府部门及企业等机构的约350名代表参会",
				[
					"reference",
					{
						"text": "赵阳. “全球南方”媒体智库高端论坛在巴西举行[EB/OL]. 新华网, 2024-11-12.https://www.news.cn/world/20241112/95a1b30eed9142a690f667c5fd7a10ff/c.html."
					}
				],
				"。"
			]
		],
		[
			"paragraph",
			[
				"一个时期以来，全球南方成为国际关系中的热词，受到国际社会各界广泛关注。今天，世界各地的人们越来越多地使用全球南方来指代新兴市场国家和发展中国家的集合体。"
			]
		],
		[
			"paragraph",
			[
				"2024年以来，中非合作论坛北京峰会在中国举办，扩员后的“大金砖”峰会在俄罗斯举行，亚太经合组织（APEC）领导人非正式会议在秘鲁登场，二十国集团峰会（G20）在巴西召开……相继举行的这些重要多边会议，点亮了全球治理的“南方时刻”，象征着“全球南方”国家在国际事务中的群体性崛起与联合性自强。"
			]
		],
		[
			"paragraph",
			[
				"这次的新华通讯社和巴西通讯公司联合主办“全球南方”媒体智库高端论坛，众多全球南方国家媒体智库相聚在一起，表明了媒体智库为全球南方团结壮大、为构建人类命运共同体鼓与呼的文化自信和历史自觉。"
			]
		],
		[
			"paragraph",
			[
				"而中国作为“全球南方”的天然成员，新华社作为作为“全球南方”媒体智库高端论坛的主办方，他们在这样一个全球治理和国际交流的重要话语平台，具体采取了哪些行动？这些行动又具有怎样的理论和实践意义？"
			]
		]
	]
}
